{"source":{"name":"OpenStreetMap solar generators via Overpass (residential-like filter)","endpoint":"https://overpass-api.de/api/interpreter","state":"Vermont","state_code":"VT","query_scope":"ISO3166-2=US-VT","filter":"power=generator, generator:source=solar, residential-like by roof/small/capacity","cell_size_deg":0.08,"imputed_system_mw":0.008,"timestamp_osm_base":"2026-04-24T23:33:16Z","license":"The data included in this document is from www.openstreetmap.org. The data is made available under ODbL.","stats":{"input_with_coords":10038,"solar_generators":10038,"residential_like_generators":136,"aggregated_cells":38}},"count":38,"rows":[{"zip":"05753","lat":44.010245,"lon":-73.185493,"projects":35,"mw_dc":0.28,"mw_ac":0.2688},{"zip":"VT-541--907","lat":43.331771,"lon":-72.52484,"projects":18,"mw_dc":0.144,"mw_ac":0.1382},{"zip":"VT-554--915","lat":44.387379,"lon":-73.130962,"projects":16,"mw_dc":0.128,"mw_ac":0.1229},{"zip":"VT-547--903","lat":43.785098,"lon":-72.22373,"projects":6,"mw_dc":0.048,"mw_ac":0.0461},{"zip":"VT-560--913","lat":44.845386,"lon":-73.00158,"projects":6,"mw_dc":0.048,"mw_ac":0.0461},{"zip":"VT-545--913","lat":43.651616,"lon":-72.988239,"projects":4,"mw_dc":0.032,"mw_ac":0.0307},{"zip":"VT-536--916","lat":42.915888,"lon":-73.237955,"projects":4,"mw_dc":0.032,"mw_ac":0.0307},{"zip":"VT-561--903","lat":44.93082,"lon":-72.218482,"projects":4,"mw_dc":0.032,"mw_ac":0.0307},{"zip":"VT-547--904","lat":43.811354,"lon":-72.289909,"projects":4,"mw_dc":0.032,"mw_ac":0.0307},{"zip":"05753","lat":43.985697,"lon":-73.138919,"projects":3,"mw_dc":0.024,"mw_ac":0.023},{"zip":"VT-547--917","lat":43.803723,"lon":-73.302321,"projects":2,"mw_dc":0.016,"mw_ac":0.0154},{"zip":"VT-538--915","lat":43.070887,"lon":-73.156467,"projects":2,"mw_dc":0.016,"mw_ac":0.0154},{"zip":"VT-555--909","lat":44.476285,"lon":-72.715379,"projects":2,"mw_dc":0.016,"mw_ac":0.0154},{"zip":"VT-551--916","lat":44.138651,"lon":-73.204669,"projects":2,"mw_dc":0.016,"mw_ac":0.0154},{"zip":"VT-545--906","lat":43.629832,"lon":-72.469985,"projects":2,"mw_dc":0.016,"mw_ac":0.0154},{"zip":"VT-555--900","lat":44.436355,"lon":-71.946137,"projects":2,"mw_dc":0.016,"mw_ac":0.0154},{"zip":"VT-535--908","lat":42.830954,"lon":-72.567981,"projects":2,"mw_dc":0.016,"mw_ac":0.0154},{"zip":"VT-545--912","lat":43.617916,"lon":-72.95603,"projects":2,"mw_dc":0.016,"mw_ac":0.0154},{"zip":"VT-543--911","lat":43.446298,"lon":-72.8258,"projects":1,"mw_dc":0.008,"mw_ac":0.0077},{"zip":"VT-554--916","lat":44.36774,"lon":-73.230343,"projects":1,"mw_dc":0.008,"mw_ac":0.0077},{"zip":"VT-551--906","lat":44.147927,"lon":-72.45801,"projects":1,"mw_dc":0.008,"mw_ac":0.0077},{"zip":"VT-560--914","lat":44.804494,"lon":-73.070583,"projects":1,"mw_dc":0.008,"mw_ac":0.0077},{"zip":"VT-554--910","lat":44.345225,"lon":-72.768064,"projects":1,"mw_dc":0.008,"mw_ac":0.0077},{"zip":"VT-541--906","lat":43.292685,"lon":-72.471409,"projects":1,"mw_dc":0.008,"mw_ac":0.0077},{"zip":"VT-547--905","lat":43.807661,"lon":-72.327127,"projects":1,"mw_dc":0.008,"mw_ac":0.0077},{"zip":"VT-553--910","lat":44.263958,"lon":-72.747173,"projects":1,"mw_dc":0.008,"mw_ac":0.0077},{"zip":"VT-555--914","lat":44.466555,"lon":-73.102354,"projects":1,"mw_dc":0.008,"mw_ac":0.0077},{"zip":"VT-556--915","lat":44.549777,"lon":-73.160657,"projects":1,"mw_dc":0.008,"mw_ac":0.0077},{"zip":"VT-535--907","lat":42.816948,"lon":-72.546317,"projects":1,"mw_dc":0.008,"mw_ac":0.0077},{"zip":"VT-548--904","lat":43.874442,"lon":-72.287769,"projects":1,"mw_dc":0.008,"mw_ac":0.0077},{"zip":"VT-545--905","lat":43.635224,"lon":-72.341928,"projects":1,"mw_dc":0.008,"mw_ac":0.0077},{"zip":"VT-545--907","lat":43.664762,"lon":-72.543986,"projects":1,"mw_dc":0.008,"mw_ac":0.0077},{"zip":"VT-540--908","lat":43.274442,"lon":-72.592489,"projects":1,"mw_dc":0.008,"mw_ac":0.0077},{"zip":"VT-538--912","lat":43.044747,"lon":-72.923792,"projects":1,"mw_dc":0.008,"mw_ac":0.0077},{"zip":"VT-544--913","lat":43.591865,"lon":-72.963671,"projects":1,"mw_dc":0.008,"mw_ac":0.0077},{"zip":"VT-556--907","lat":44.481064,"lon":-72.501643,"projects":1,"mw_dc":0.008,"mw_ac":0.0077},{"zip":"VT-549--903","lat":43.98579,"lon":-72.168156,"projects":1,"mw_dc":0.008,"mw_ac":0.0077},{"zip":"VT-561--911","lat":44.908013,"lon":-72.822796,"projects":1,"mw_dc":0.008,"mw_ac":0.0077}]}
